focus_tools/__init__.py
focus_tools/focus_tools.py
focus_tools/multifocal.py
focus_tools/pydls.py
focus_tools/pykriber.py
focus_tools/bin_linux/_dls76.x
focus_tools/bin_linux/_kriber.x
focus_tools/bin_linux/focus
focus_tools/bin_linux/sginfo
focus_tools/bin_osx/_dls76.x
focus_tools/bin_osx/_kriber.x
focus_tools/bin_osx/focus
focus_tools/bin_osx/sginfo
focus_tools/bin_windows/_dls76.x
focus_tools/bin_windows/_kriber.x
focus_tools/bin_windows/focus.exe
focus_tools/bin_windows/libfftw3f-3.dll
focus_tools/bin_windows/sginfo.exe
focus_tools/resources/coseq
focus_tools/resources/distdat
focus_tools/resources/spgr.dat
focus_tools/resources/symdat
focus_package-3.1.0.dist-info/LICENCE
focus_package-3.1.0.dist-info/METADATA
focus_package-3.1.0.dist-info/WHEEL
focus_package-3.1.0.dist-info/entry_points.txt
focus_package-3.1.0.dist-info/top_level.txt
focus_package-3.1.0.dist-info/RECORD
