Metadata-Version: 2.1
Name: focus-package
Version: 3.1.0
Summary: FOCUS package including DLS-76 and KRIBER
Home-page: https://github.com/stefsmeets/focus_package
Author: Stef Smeets
Author-email: s.smeets@esciencecenter.nl
Project-URL: Bug Tracker, https://github.com/stefsmeets/focus_package/issues
Project-URL: Documentation, https://github.com/stefsmeets/focus_package
Keywords: focus,zeolites,structure-determination,dls76,kriber,electron-diffraction-data,powder-diffraction-data
Classifier: Development Status :: 5 - Production/Stable
Classifier: Intended Audience :: Developers
Classifier: Intended Audience :: Science/Research
Classifier: License :: OSI Approved :: GNU General Public License v2 (GPLv2)
Classifier: Natural Language :: English
Classifier: Programming Language :: Python :: 3
Classifier: Programming Language :: Python :: 3.9
Classifier: Programming Language :: Python :: 3.10
Classifier: Programming Language :: Python :: 3.11
Classifier: Topic :: Scientific/Engineering
License-File: LICENCE
Requires-Dist: importlib-resources ; python_version < "3.10"
Provides-Extra: build
Requires-Dist: twine ; extra == 'build'
Requires-Dist: wheel ; extra == 'build'
Requires-Dist: build ; extra == 'build'
